src/mux_4x1.v
module mux_4x1(input wire [3:0] i, input wire [1:0] s, output wire z);
  // Preserve the original lab ordering: 00 -> i[3].
  assign z = i[3-s];
  endmodule

sim/tb_mux_4x1.sv
`timescale 1ns/1ps
module tb_mux_4x1;
  reg [3:0] i; reg [1:0] s; wire z; mux_4x1 dut(i,s,z);
  integer n,checked=0;
  reg [0:0] expected;
  initial begin
    $dumpfile("wave.vcd"); $dumpvars(0,tb_mux_4x1);

    for(n=0;n<64;n=n+1) begin
      {i,s}=n;
      expected=((n/4) >> (3-(n%4))) & 1;
      #10;
      if (z !== expected) begin
        $fatal(1,"LAB1 mux_4x1 vector:%0d expected=%h actual=%h",n,expected,z);
      end
      checked=checked+1;
    end
    if(checked!=64) $fatal(1,"incomplete test");
    $display("LAB1_PASS mux_4x1 cases=%0d",checked);
    $finish;
  end
  initial begin #100000; $fatal(1,"Watchdog"); end
endmodule

mux_4x1.sim/sim_1/behav/xsim/wave.vcd
$date
   Tue Sep 15 11:22:42 2026
$end

$version
  2026.1
  $dumpfile ("wave.vcd") 
$end

$timescale
  1ps
$end

$scope module tb_mux_4x1 $end
$var reg 4 ! i [3:0] $end
$var reg 2 " s [1:0] $end
$var wire 1 # z $end
$var integer 32 $ n [31:0] $end
$var integer 32 % checked [31:0] $end
$var reg 1 & expected [0:0] $end
$scope module dut $end
$var wire 4 ' i [3:0] $end
$var wire 2 ( s [1:0] $end
$var wire 1 # z $end
$upscope $end
$upscope $end
$enddefinitions $end

#0
$dumpvars
b0 !
b0 "
0#
b0 $
b0 %
0&
b0 '
b0 (
$end

#10000
b1 "
b1 $
b1 %
b1 (

#20000
b10 "
b10 $
b10 %
b10 (

#30000
b11 "
b11 $
b11 %
b11 (

#40000
b1 !
b0 "
b100 $
b100 %
b1 '
b0 (

#50000
b1 "
b101 $
b101 %
b1 (

#60000
b10 "
b110 $
b110 %
b10 (

#70000
b11 "
1#
b111 $
b111 %
1&
b11 (

#80000
b10 !
b0 "
0#
b1000 $
b1000 %
0&
b10 '
b0 (

#90000
b1 "
b1001 $
b1001 %
b1 (

#100000
b10 "
1#
b1010 $
b1010 %
1&
b10 (

#110000
b11 "
0#
b1011 $
b1011 %
0&
b11 (

#120000
b11 !
b0 "
b1100 $
b1100 %
b11 '
b0 (

#130000
b1 "
b1101 $
b1101 %
b1 (

#140000
b10 "
1#
b1110 $
b1110 %
1&
b10 (

#150000
b11 "
b1111 $
b1111 %
b11 (

#160000
b100 !
b0 "
0#
b10000 $
b10000 %
0&
b100 '
b0 (

#170000
b1 "
1#
b10001 $
b10001 %
1&
b1 (

#180000
b10 "
0#
b10010 $
b10010 %
0&
b10 (

#190000
b11 "
b10011 $
b10011 %
b11 (

#200000
b101 !
b0 "
b10100 $
b10100 %
b101 '
b0 (

#210000
b1 "
1#
b10101 $
b10101 %
1&
b1 (

#220000
b10 "
0#
b10110 $
b10110 %
0&
b10 (

#230000
b11 "
1#
b10111 $
b10111 %
1&
b11 (

#240000
b110 !
b0 "
0#
b11000 $
b11000 %
0&
b110 '
b0 (

#250000
b1 "
1#
b11001 $
b11001 %
1&
b1 (

#260000
b10 "
b11010 $
b11010 %
b10 (

#270000
b11 "
0#
b11011 $
b11011 %
0&
b11 (

#280000
b111 !
b0 "
b11100 $
b11100 %
b111 '
b0 (

#290000
b1 "
1#
b11101 $
b11101 %
1&
b1 (

#300000
b10 "
b11110 $
b11110 %
b10 (

#310000
b11 "
b11111 $
b11111 %
b11 (

#320000
b1000 !
b0 "
b100000 $
b100000 %
b1000 '
b0 (

#330000
b1 "
0#
b100001 $
b100001 %
0&
b1 (

#340000
b10 "
b100010 $
b100010 %
b10 (

#350000
b11 "
b100011 $
b100011 %
b11 (

#360000
b1001 !
b0 "
1#
b100100 $
b100100 %
1&
b1001 '
b0 (

#370000
b1 "
0#
b100101 $
b100101 %
0&
b1 (

#380000
b10 "
b100110 $
b100110 %
b10 (

#390000
b11 "
1#
b100111 $
b100111 %
1&
b11 (

#400000
b1010 !
b0 "
b101000 $
b101000 %
b1010 '
b0 (

#410000
b1 "
0#
b101001 $
b101001 %
0&
b1 (

#420000
b10 "
1#
b101010 $
b101010 %
1&
b10 (

#430000
b11 "
0#
b101011 $
b101011 %
0&
b11 (

#440000
b1011 !
b0 "
1#
b101100 $
b101100 %
1&
b1011 '
b0 (

#450000
b1 "
0#
b101101 $
b101101 %
0&
b1 (

#460000
b10 "
1#
b101110 $
b101110 %
1&
b10 (

#470000
b11 "
b101111 $
b101111 %
b11 (

#480000
b1100 !
b0 "
b110000 $
b110000 %
b1100 '
b0 (

#490000
b1 "
b110001 $
b110001 %
b1 (

#500000
b10 "
0#
b110010 $
b110010 %
0&
b10 (

#510000
b11 "
b110011 $
b110011 %
b11 (

#520000
b1101 !
b0 "
1#
b110100 $
b110100 %
1&
b1101 '
b0 (

#530000
b1 "
b110101 $
b110101 %
b1 (

#540000
b10 "
0#
b110110 $
b110110 %
0&
b10 (

#550000
b11 "
1#
b110111 $
b110111 %
1&
b11 (

#560000
b1110 !
b0 "
b111000 $
b111000 %
b1110 '
b0 (

#570000
b1 "
b111001 $
b111001 %
b1 (

#580000
b10 "
b111010 $
b111010 %
b10 (

#590000
b11 "
0#
b111011 $
b111011 %
0&
b11 (

#600000
b1111 !
b0 "
1#
b111100 $
b111100 %
1&
b1111 '
b0 (

#610000
b1 "
b111101 $
b111101 %
b1 (

#620000
b10 "
b111110 $
b111110 %
b10 (

#630000
b11 "
b111111 $
b111111 %
b11 (

#640000
b1000000 $
b1000000 %
